Workbook

Sheet Dashboard
A1: CAAD ERP Executive Summary | D1: Payment Type | E1: Revenue | F1: Share %
A2: Total Revenue | B2: =SUM(TransactionLog!H:H)/100 | D2: Cash | E2: =SUMIFS(TransactionLog!H:H, TransactionLog!F:F, "Cash", TransactionLog!C:C, "SALE")/100 | F2: =IFERROR(E2/$B$2, 0)
A3: Total Costs / Expenses | B3: =SUM(TransactionLog!I:I)/100 | D3: PIX | E3: =SUMIFS(TransactionLog!H:H, TransactionLog!F:F, "PIX", TransactionLog!C:C, "SALE")/100 | F3: =IFERROR(E3/$B$2, 0)
A4: Net Profit | B4: =B2+B3 | D4: OnCredit | E4: =SUMIFS(TransactionLog!H:H, TransactionLog!F:F, "OnCredit", TransactionLog!C:C, "SALE")/100 | F4: =IFERROR(E4/$B$2, 0)
A5: Profit Margin | B5: =IFERROR((B2+B3)/B2, 0) | D5: Other | E5: =SUMIFS(TransactionLog!H:H, TransactionLog!F:F, "Other", TransactionLog!C:C, "SALE")/100 | F5: =IFERROR(E5/$B$2, 0)
A6: Outstanding Debts | B6: =(SUMIF(TransactionLog!F:F, "OnCredit", TransactionLog!H:H) - SUMIF(TransactionLog!C:C, "CREDIT_PAYMENT", TransactionLog!H:H))/100
A16: Salesman Name | B16: Deals Closed | C16: Deals Rank | D16: Total Revenue | E16: Revenue Rank | F16: % of Total
A17: =IF(Salesmen!B2="","",Salesmen!B2) | B17: =IF(A17="","",COUNTIFS(TransactionLog!E:E, Salesmen!A2, TransactionLog!C:C, "SALE")) | C17: =IF(A17="","",RANK(B17, $B$17:$B$26)) | D17: =IF(A17="","",SUMIFS(TransactionLog!H:H, TransactionLog!E:E, Salesmen!A2, TransactionLog!C:C, "SALE")/100) | E17: =IF(A17="","",RANK(D17, $D$17:$D$26)) | F17: =IF(A17="","",IFERROR(D17/$B$2, 0))
A18: =IF(Salesmen!B3="","",Salesmen!B3) | B18: =IF(A18="","",COUNTIFS(TransactionLog!E:E, Salesmen!A3, TransactionLog!C:C, "SALE")) | C18: =IF(A18="","",RANK(B18, $B$17:$B$26)) | D18: =IF(A18="","",SUMIFS(TransactionLog!H:H, TransactionLog!E:E, Salesmen!A3, TransactionLog!C:C, "SALE")/100) | E18: =IF(A18="","",RANK(D18, $D$17:$D$26)) | F18: =IF(A18="","",IFERROR(D18/$B$2, 0))
A19: =IF(Salesmen!B4="","",Salesmen!B4) | B19: =IF(A19="","",COUNTIFS(TransactionLog!E:E, Salesmen!A4, TransactionLog!C:C, "SALE")) | C19: =IF(A19="","",RANK(B19, $B$17:$B$26)) | D19: =IF(A19="","",SUMIFS(TransactionLog!H:H, TransactionLog!E:E, Salesmen!A4, TransactionLog!C:C, "SALE")/100) | E19: =IF(A19="","",RANK(D19, $D$17:$D$26)) | F19: =IF(A19="","",IFERROR(D19/$B$2, 0))
A20: =IF(Salesmen!B5="","",Salesmen!B5) | B20: =IF(A20="","",COUNTIFS(TransactionLog!E:E, Salesmen!A5, TransactionLog!C:C, "SALE")) | C20: =IF(A20="","",RANK(B20, $B$17:$B$26)) | D20: =IF(A20="","",SUMIFS(TransactionLog!H:H, TransactionLog!E:E, Salesmen!A5, TransactionLog!C:C, "SALE")/100) | E20: =IF(A20="","",RANK(D20, $D$17:$D$26)) | F20: =IF(A20="","",IFERROR(D20/$B$2, 0))
A21: =IF(Salesmen!B6="","",Salesmen!B6) | B21: =IF(A21="","",COUNTIFS(TransactionLog!E:E, Salesmen!A6, TransactionLog!C:C, "SALE")) | C21: =IF(A21="","",RANK(B21, $B$17:$B$26)) | D21: =IF(A21="","",SUMIFS(TransactionLog!H:H, TransactionLog!E:E, Salesmen!A6, TransactionLog!C:C, "SALE")/100) | E21: =IF(A21="","",RANK(D21, $D$17:$D$26)) | F21: =IF(A21="","",IFERROR(D21/$B$2, 0))
A22: =IF(Salesmen!B7="","",Salesmen!B7) | B22: =IF(A22="","",COUNTIFS(TransactionLog!E:E, Salesmen!A7, TransactionLog!C:C, "SALE")) | C22: =IF(A22="","",RANK(B22, $B$17:$B$26)) | D22: =IF(A22="","",SUMIFS(TransactionLog!H:H, TransactionLog!E:E, Salesmen!A7, TransactionLog!C:C, "SALE")/100) | E22: =IF(A22="","",RANK(D22, $D$17:$D$26)) | F22: =IF(A22="","",IFERROR(D22/$B$2, 0))
A23: =IF(Salesmen!B8="","",Salesmen!B8) | B23: =IF(A23="","",COUNTIFS(TransactionLog!E:E, Salesmen!A8, TransactionLog!C:C, "SALE")) | C23: =IF(A23="","",RANK(B23, $B$17:$B$26)) | D23: =IF(A23="","",SUMIFS(TransactionLog!H:H, TransactionLog!E:E, Salesmen!A8, TransactionLog!C:C, "SALE")/100) | E23: =IF(A23="","",RANK(D23, $D$17:$D$26)) | F23: =IF(A23="","",IFERROR(D23/$B$2, 0))
A24: =IF(Salesmen!B9="","",Salesmen!B9) | B24: =IF(A24="","",COUNTIFS(TransactionLog!E:E, Salesmen!A9, TransactionLog!C:C, "SALE")) | C24: =IF(A24="","",RANK(B24, $B$17:$B$26)) | D24: =IF(A24="","",SUMIFS(TransactionLog!H:H, TransactionLog!E:E, Salesmen!A9, TransactionLog!C:C, "SALE")/100) | E24: =IF(A24="","",RANK(D24, $D$17:$D$26)) | F24: =IF(A24="","",IFERROR(D24/$B$2, 0))
A25: =IF(Salesmen!B10="","",Salesmen!B10) | B25: =IF(A25="","",COUNTIFS(TransactionLog!E:E, Salesmen!A10, TransactionLog!C:C, "SALE")) | C25: =IF(A25="","",RANK(B25, $B$17:$B$26)) | D25: =IF(A25="","",SUMIFS(TransactionLog!H:H, TransactionLog!E:E, Salesmen!A10, TransactionLog!C:C, "SALE")/100) | E25: =IF(A25="","",RANK(D25, $D$17:$D$26)) | F25: =IF(A25="","",IFERROR(D25/$B$2, 0))
A26: =IF(Salesmen!B11="","",Salesmen!B11) | B26: =IF(A26="","",COUNTIFS(TransactionLog!E:E, Salesmen!A11, TransactionLog!C:C, "SALE")) | C26: =IF(A26="","",RANK(B26, $B$17:$B$26)) | D26: =IF(A26="","",SUMIFS(TransactionLog!H:H, TransactionLog!E:E, Salesmen!A11, TransactionLog!C:C, "SALE")/100) | E26: =IF(A26="","",RANK(D26, $D$17:$D$26)) | F26: =IF(A26="","",IFERROR(D26/$B$2, 0))
A28: ProductID | B28: ProductName | C28: Stock On Hand | D28: Total Sales Revenue | E28: Stock Status Alert
A29: =IF(Products!A2="","",Products!A2) | B29: =IF(A29="","",Products!B2) | C29: =IF(A29="","",SUMIF(TransactionLog!D:D, A29, TransactionLog!G:G)) | D29: =IF(A29="","",SUMIFS(TransactionLog!H:H, TransactionLog!D:D, A29, TransactionLog!C:C, "SALE")/100) | E29: =IF(A29="","",IF(C29<=0, "OUT OF STOCK", IF(C29<=5, "LOW STOCK", "OK")))
A30: =IF(Products!A3="","",Products!A3) | B30: =IF(A30="","",Products!B3) | C30: =IF(A30="","",SUMIF(TransactionLog!D:D, A30, TransactionLog!G:G)) | D30: =IF(A30="","",SUMIFS(TransactionLog!H:H, TransactionLog!D:D, A30, TransactionLog!C:C, "SALE")/100) | E30: =IF(A30="","",IF(C30<=0, "OUT OF STOCK", IF(C30<=5, "LOW STOCK", "OK")))
A31: =IF(Products!A4="","",Products!A4) | B31: =IF(A31="","",Products!B4) | C31: =IF(A31="","",SUMIF(TransactionLog!D:D, A31, TransactionLog!G:G)) | D31: =IF(A31="","",SUMIFS(TransactionLog!H:H, TransactionLog!D:D, A31, TransactionLog!C:C, "SALE")/100) | E31: =IF(A31="","",IF(C31<=0, "OUT OF STOCK", IF(C31<=5, "LOW STOCK", "OK")))
A32: =IF(Products!A5="","",Products!A5) | B32: =IF(A32="","",Products!B5) | C32: =IF(A32="","",SUMIF(TransactionLog!D:D, A32, TransactionLog!G:G)) | D32: =IF(A32="","",SUMIFS(TransactionLog!H:H, TransactionLog!D:D, A32, TransactionLog!C:C, "SALE")/100) | E32: =IF(A32="","",IF(C32<=0, "OUT OF STOCK", IF(C32<=5, "LOW STOCK", "OK")))
A33: =IF(Products!A6="","",Products!A6) | B33: =IF(A33="","",Products!B6) | C33: =IF(A33="","",SUMIF(TransactionLog!D:D, A33, TransactionLog!G:G)) | D33: =IF(A33="","",SUMIFS(TransactionLog!H:H, TransactionLog!D:D, A33, TransactionLog!C:C, "SALE")/100) | E33: =IF(A33="","",IF(C33<=0, "OUT OF STOCK", IF(C33<=5, "LOW STOCK", "OK")))
A34: =IF(Products!A7="","",Products!A7) | B34: =IF(A34="","",Products!B7) | C34: =IF(A34="","",SUMIF(TransactionLog!D:D, A34, TransactionLog!G:G)) | D34: =IF(A34="","",SUMIFS(TransactionLog!H:H, TransactionLog!D:D, A34, TransactionLog!C:C, "SALE")/100) | E34: =IF(A34="","",IF(C34<=0, "OUT OF STOCK", IF(C34<=5, "LOW STOCK", "OK")))
A35: =IF(Products!A8="","",Products!A8) | B35: =IF(A35="","",Products!B8) | C35: =IF(A35="","",SUMIF(TransactionLog!D:D, A35, TransactionLog!G:G)) | D35: =IF(A35="","",SUMIFS(TransactionLog!H:H, TransactionLog!D:D, A35, TransactionLog!C:C, "SALE")/100) | E35: =IF(A35="","",IF(C35<=0, "OUT OF STOCK", IF(C35<=5, "LOW STOCK", "OK")))
A36: =IF(Products!A9="","",Products!A9) | B36: =IF(A36="","",Products!B9) | C36: =IF(A36="","",SUMIF(TransactionLog!D:D, A36, TransactionLog!G:G)) | D36: =IF(A36="","",SUMIFS(TransactionLog!H:H, TransactionLog!D:D, A36, TransactionLog!C:C, "SALE")/100) | E36: =IF(A36="","",IF(C36<=0, "OUT OF STOCK", IF(C36<=5, "LOW STOCK", "OK")))
A37: =IF(Products!A10="","",Products!A10) | B37: =IF(A37="","",Products!B10) | C37: =IF(A37="","",SUMIF(TransactionLog!D:D, A37, TransactionLog!G:G)) | D37: =IF(A37="","",SUMIFS(TransactionLog!H:H, TransactionLog!D:D, A37, TransactionLog!C:C, "SALE")/100) | E37: =IF(A37="","",IF(C37<=0, "OUT OF STOCK", IF(C37<=5, "LOW STOCK", "OK")))
A38: =IF(Products!A11="","",Products!A11) | B38: =IF(A38="","",Products!B11) | C38: =IF(A38="","",SUMIF(TransactionLog!D:D, A38, TransactionLog!G:G)) | D38: =IF(A38="","",SUMIFS(TransactionLog!H:H, TransactionLog!D:D, A38, TransactionLog!C:C, "SALE")/100) | E38: =IF(A38="","",IF(C38<=0, "OUT OF STOCK", IF(C38<=5, "LOW STOCK", "OK")))
A39: =IF(Products!A12="","",Products!A12) | B39: =IF(A39="","",Products!B12) | C39: =IF(A39="","",SUMIF(TransactionLog!D:D, A39, TransactionLog!G:G)) | D39: =IF(A39="","",SUMIFS(TransactionLog!H:H, TransactionLog!D:D, A39, TransactionLog!C:C, "SALE")/100) | E39: =IF(A39="","",IF(C39<=0, "OUT OF STOCK", IF(C39<=5, "LOW STOCK", "OK")))
A40: =IF(Products!A13="","",Products!A13) | B40: =IF(A40="","",Products!B13) | C40: =IF(A40="","",SUMIF(TransactionLog!D:D, A40, TransactionLog!G:G)) | D40: =IF(A40="","",SUMIFS(TransactionLog!H:H, TransactionLog!D:D, A40, TransactionLog!C:C, "SALE")/100) | E40: =IF(A40="","",IF(C40<=0, "OUT OF STOCK", IF(C40<=5, "LOW STOCK", "OK")))
... A78: =IF(Products!A51="","",Products!A51) | B78: =IF(A78="","",Products!B51) | C78: =IF(A78="","",SUMIF(TransactionLog!D:D, A78, TransactionLog!G:G)) | D78: =IF(A78="","",SUMIFS(TransactionLog!H:H, TransactionLog!D:D, A78, TransactionLog!C:C, "SALE")/100) | E78: =IF(A78="","",IF(C78<=0, "OUT OF STOCK", IF(C78<=5, "LOW STOCK", "OK")))

Sheet Products
A1: ProductID | B1: ProductName | C1: SellPrice | D1: IsActive

Sheet Salesmen
A1: SalesmanID | B1: SalesmanName | C1: IsActive

Sheet TransactionLog
A1: TransactionID | B1: Timestamp | C1: TransactionType | D1: ProductID | E1: SalesmanID | F1: PaymentType | G1: QuantityChange | H1: TotalRevenue | I1: TotalCost | J1: LinkedTransactionID | K1: Notes
